[
    {
        "date": "31 de enero de 2024",
        "date event": "TO_BE_FILLED_IN"
    },
    {
        "date": "29 de diciembre de 2022",
        "date event": "TO_BE_FILLED_IN"
    },
    {
        "date": "07 de octubre del 2022",
        "date event": "TO_BE_FILLED_IN"
    },
    {
        "date": "11 de octubre del 2022",
        "date event": "TO_BE_FILLED_IN"
    },
    {
        "date": "06 de octubre del 2022",
        "date event": "TO_BE_FILLED_IN"
    },
    {
        "date": "10 de febrero de 2023",
        "date event": "TO_BE_FILLED_IN"
    },
    {
        "date": "15 de febrero de 2023",
        "date event": "TO_BE_FILLED_IN"
    },
    {
        "date": "3 de marzo de 2023",
        "date event": "TO_BE_FILLED_IN"
    },
    {
        "date": "29 de marzo de 2023",
        "date event": "TO_BE_FILLED_IN"
    },
    {
        "date": "7 de febrero de 2017",
        "date event": "TO_BE_FILLED_IN"
    },
    {
        "date": "3 de diciembre del 2008",
        "date event": "TO_BE_FILLED_IN"
    }
]